akid/__init__.py
akid/backend/__init__.py
akid/backend/computational_graph.py
akid/backend/tf_backend/__init__.py
akid/backend/tf_backend/computational_graph.py
akid/backend/tf_backend/nn.py
akid/backend/tf_backend/summary.py
akid/backend/tf_backend/train.py
akid/backend/th_backend/__init__.py
akid/backend/th_backend/computational_graph.py
akid/backend/th_backend/nn.py
akid/backend/th_backend/summary.py
akid/backend/th_backend/train.py
akid/core/__init__.py
akid/core/blocks.py
akid/core/brains.py
akid/core/callbacks.py
akid/core/common.py
akid/core/engines.py
akid/core/eval_blocks.py
akid/core/events.py
akid/core/initializers.py
akid/core/interface_blocks.py
akid/core/jokers.py
akid/core/kids.py
akid/core/kongfus.py
akid/core/observer.py
akid/core/samplers.py
akid/core/sensors.py
akid/core/sources.py
akid/core/systems.py
akid/datasets/__init__.py
akid/datasets/cifar10.py
akid/datasets/cifar100.py
akid/datasets/datasets.py
akid/datasets/imagenet.py
akid/datasets/mnist.py
akid/examples/__init__.py
akid/examples/alex_net.py
akid/examples/dist_akid.py
akid/examples/imagenet.py
akid/examples/jinja2_maxout.py
akid/examples/spcnn.py
akid/examples/vgg.py
akid/examples/mnist/__init__.py
akid/examples/mnist/block_mnist.py
akid/examples/mnist/mnist.py
akid/examples/mnist/mnist_tf_tutorial.py
akid/layers/__init__.py
akid/layers/activation_layers.py
akid/layers/common_layers.py
akid/layers/eval_layers.py
akid/layers/loss_layers.py
akid/layers/memory_layers.py
akid/layers/synapse_layers.py
akid/models/__init__.py
akid/models/brains.py
akid/nn/__init__.py
akid/nn/accuracy.py
akid/nn/losses.py
akid/nn/regularizers.py
akid/ops/__init__.py
akid/ops/image_ops.py
akid/ops/matrix_ops.py
akid/ops/random_ops.py
akid/parallel/__init__.py
akid/parallel/functions.py
akid/sugar/__init__.py
akid/sugar/block_templates.py
akid/tf_tutorial/__init__.py
akid/tf_tutorial/input_data.py
akid/tf_tutorial/mnist.py
akid/tf_tutorial/train.py
akid/train/__init__.py
akid/train/get_accuracy.py
akid-0.2.dist-info/LICENSE
akid-0.2.dist-info/METADATA
akid-0.2.dist-info/WHEEL
akid-0.2.dist-info/top_level.txt
akid-0.2.dist-info/RECORD
