Metadata-Version: 2.1
Name: akid
Version: 0.2
Summary: A python package to study the theory of Deep Neural Networks
Home-page: https://github.com/shawnLeeZX/akid
Author: Shuai Li
Author-email: lishuai918@gmail.com
License: UNKNOWN
Platform: UNKNOWN
Classifier: Programming Language :: Python :: 3
Classifier: License :: OSI Approved :: GNU General Public License v3 (GPLv3)
Classifier: Operating System :: OS Independent
Requires-Python: >=3.6
